MathP/__init__.py
MathP/math_learn.py
MathP/math_source.csv
MathP/math_statistic.py
mathp-0.1.3.dist-info/METADATA
mathp-0.1.3.dist-info/WHEEL
mathp-0.1.3.dist-info/licenses/LICENSE
mathp-0.1.3.dist-info/RECORD
