Metadata-Version: 2.1
Name: MathP
Version: 0.1.3
Summary: It is a tool to learn how to read and write Chinese Characters.
Project-URL: Homepage, https://gitee.com/shawnyanwang/chinese-learning-tool
Project-URL: Bug Tracker, https://gitee.com/shawnyanwang/chinese-learning-tool/issues
Author-email: shawn yan wang <shawnyanwang@gmail.com>
Classifier: License :: OSI Approved :: MIT License
Classifier: Operating System :: OS Independent
Classifier: Programming Language :: Python :: 3
Requires-Python: >=3.7
Requires-Dist: matplotlib>=3.5.1
Requires-Dist: pandas>=1.3.4
